LICENSE.txt
MANIFEST.in
README.rst
setup.cfg
setup.py
WTForms_Django_alex.egg-info/PKG-INFO
WTForms_Django_alex.egg-info/SOURCES.txt
WTForms_Django_alex.egg-info/dependency_links.txt
WTForms_Django_alex.egg-info/requires.txt
WTForms_Django_alex.egg-info/top_level.txt
docs/Makefile
docs/conf.py
docs/index.rst
docs/make.bat
docs/wtforms_django.rst
tests/__init__.py
tests/django_setup.py
tests/models.py
tests/requirements.txt
tests/runtests.py
tests/test_basic.py
tests/test_timezone.py
tests/utils.py
tests/fixtures/ext_django.json
wtforms_django/__init__.py
wtforms_django/apps.py
wtforms_django/fields.py
wtforms_django/i18n.py
wtforms_django/orm.py
wtforms_django/templatetags/__init__.py
wtforms_django/templatetags/wtforms.py